<?xml version="1.0" encoding="UTF-8"?>
<!--
Click nbfs://nbhost/SystemFileSystem/Templates/Licenses/license-default.txt to change this license
Click nbfs://nbhost/SystemFileSystem/Templates/XML/XMLDocument.xml to edit this template
-->
<!DOCTYPE tiles-definitions PUBLIC "-//Apache Software Foundation//DTD Tiles Configuration 3.0//EN"
"http://tiles.apache.org/dtds/tiles-config_3_0.dtd">

<tiles-definitions>
    <definition name="baseLayout" template="/WEB-INF/layout/base.jsp">
        <put-attribute name="title" value="" />
        <put-attribute name="header" value="/WEB-INF/layout/header.jsp" />
        <put-attribute name="footer" value="/WEB-INF/layout/footer.jsp" />
        <put-attribute name="content" value="" />
    </definition>
    <definition name="index" extends="baseLayout">
        <put-attribute name="title" value="SOCIAL NETWORK ADMINISTRATION" />
        <put-attribute name="content" value="/WEB-INF/pages/index.jsp" />
    </definition>
    <definition name="user" extends="baseLayout">
        <put-attribute name="title" value="USER ADMINISTRATION" />
        <put-attribute name="content" value="/WEB-INF/pages/user.jsp" />
    </definition>
    <definition name="createLecturer" extends="baseLayout">
        <put-attribute name="title" value="CREATE LECTURER ADMINISTRATION" />
        <put-attribute name="content" value="/WEB-INF/pages/createLecturer.jsp" />
    </definition>
    <definition name="statistics" extends="baseLayout">
        <put-attribute name="title" value="STATISTICS" />
        <put-attribute name="content" value="/WEB-INF/pages/statistics.jsp" />
    </definition>
</tiles-definitions>

